source/__init__.py
source/context.py
source/errors/parallel_task_requires_tasks_exception.py
source/errors/saga_compensation_execution_exception.py
source/errors/saga_execution_exception.py
source/errors/task_execution_exception.py
source/logging/saga_logging.py
source/parallel_task.py
source/saga.py
source/task.py
source/task_status.py
saga_framework_python-0.0.2.dist-info/LICENSE
saga_framework_python-0.0.2.dist-info/METADATA
saga_framework_python-0.0.2.dist-info/WHEEL
saga_framework_python-0.0.2.dist-info/RECORD
