Metadata-Version: 2.1
Name: saga-framework-python
Version: 0.0.2
Summary: A python framework for implementing a saga pattern.
Author: PrashaanPillay
Requires-Python: ==3.12.5
Classifier: Programming Language :: Python :: 3
Requires-Dist: loguru (>=0.7.2,<0.8.0)
Requires-Dist: mypy (>=1.11.2,<2.0.0)
Requires-Dist: poetry-dynamic-versioning (>=1.4.1,<2.0.0)
Requires-Dist: pytest (>=8.3.3,<9.0.0)
Requires-Dist: pytest-cov (>=5.0.0,<6.0.0)
Requires-Dist: pytest-repeat (>=0.9.3,<0.10.0)
Requires-Dist: pytest-socket (>=0.7.0,<0.8.0)
Requires-Dist: pytest-sugar (>=1.0.0,<2.0.0)
Requires-Dist: pytest-xdist (>=3.6.1,<4.0.0)
Requires-Dist: python-semantic-release (>=9.8.8,<10.0.0)
Requires-Dist: ruff (>=0.6.7,<0.7.0)
Requires-Dist: twine (>=5.1.1,<6.0.0)
